anilist_api/__init__.py
anilist_api/anime.py
anilist_api/character.py
anilist_api/config.py
anilist_api/exceptions.py
anilist_api/graphql.py
anilist_api/manga.py
anilist_api/user.py
anilist_api-0.1.0.dist-info/LICENSE
anilist_api-0.1.0.dist-info/METADATA
anilist_api-0.1.0.dist-info/WHEEL
anilist_api-0.1.0.dist-info/top_level.txt
anilist_api-0.1.0.dist-info/RECORD
