Metadata-Version: 2.1
Name: anilist-api
Version: 0.1.0
Summary: A complete Python wrapper for AniList GraphQL API
Home-page: https://github.com/anbuinfosec/anilist-api
Author: Mohammad Alamin
Author-email: anbuinfosec@gmail.com
License: MIT
Project-URL: Bug Tracker, https://github.com/anbuinfosec/anilist-api/issues
Project-URL: Documentation, https://github.com/anbuinfosec/anilist-api#readme
Project-URL: Source, https://github.com/anbuinfosec/anilist-api
Project-URL: Homepage, https://github.com/anbuinfosec/anilist-api
Keywords: anilist,graphql,api,wrapper,python,anime,manga,anbuinfosec
Platform: UNKNOWN
Classifier: Programming Language :: Python :: 3
Classifier: License :: OSI Approved :: MIT License
Classifier: Operating System :: OS Independent
Classifier: Topic :: Software Development :: Libraries :: Python Modules
Classifier: Intended Audience :: Developers
Requires-Python: >=3.7
License-File: LICENSE
Requires-Dist: requests
